django_serverside_datatable/__init__.py
django_serverside_datatable/datatable.py
django_serverside_datatable/views.py
django_serverside_datatable-2.1.0.dist-info/LICENSE
django_serverside_datatable-2.1.0.dist-info/METADATA
django_serverside_datatable-2.1.0.dist-info/WHEEL
django_serverside_datatable-2.1.0.dist-info/top_level.txt
django_serverside_datatable-2.1.0.dist-info/RECORD
