Metadata-Version: 2.1
Name: django-serverside-datatable
Version: 2.1.0
Summary: Simple Server-side Datatable processing view for Django
Home-page: https://github.com/umesh-krishna/django_serverside_datatable
Author: Umesh Krishna
Author-email: umesh_krishna@outlook.com
License: MIT
Classifier: Programming Language :: Python :: 3
Classifier: License :: OSI Approved :: MIT License
Classifier: Operating System :: OS Independent
Requires-Python: >=3.6
License-File: LICENSE
